README.md
setup.py
SimpleMiddleware/__init__.py
SimpleMiddleware/middleware.py
drf_simplemiddleware_logger.egg-info/PKG-INFO
drf_simplemiddleware_logger.egg-info/SOURCES.txt
drf_simplemiddleware_logger.egg-info/dependency_links.txt
drf_simplemiddleware_logger.egg-info/requires.txt
drf_simplemiddleware_logger.egg-info/top_level.txt